spacetornado/__init__.py
spacetornado/handlers.py
spacetornado/operations.py
spacetornado/server.py
spacetornado/spacetornado.py
spacetornado-0.1.dist-info/METADATA
spacetornado-0.1.dist-info/WHEEL
spacetornado-0.1.dist-info/entry_points.txt
spacetornado-0.1.dist-info/top_level.txt
spacetornado-0.1.dist-info/RECORD
